{
    "badges": [
        {
            "title": "Volunteering Streak",
            "description": "Recognized for maintaining a consistent volunteering streak for 3 months.",
            "pre_requisites": "Attend and participate in at least one volunteering event every month for 3 consecutive months.",
            "image": ""
        },
        {
            "title": "Personal Supporter",
            "description": "Recognized for providing personalized assistance in a one-on-one service event.",
            "pre_requisites": "Participate in a private volunteering event, such as one-on-one counseling or support service.",
            "image": ""
        },
        {
            "title": "Dedicated Volunteer",
            "description": "Acknowledged for your commitment to participating in over 20 volunteer activities.",
            "pre_requisites": "Participate in more than 20 volunteering events.",
            "image": ""
        }
    ]
}
